{
  "title": "Disobedience",
  "tagline": "Love is an act of defiance",
  "id": 419743,
  "overview": "A woman learns about the death of her Orthodox Jewish father, a rabbi. She returns home and has romantic feelings rekindled for her best childhood friend, who is now married to her cousin.",
  "releaseDate": "2018-04-24",
  "runtime": 114,
  "companies": [
    "Braven Films",
    "Element Pictures",
    "Film4 Productions",
    "LC6 Productions"
  ],
  "genres": [
    "Drama",
    "Romance"
  ]
}