{
  "title": "The Hobbit: The Desolation of Smaug",
  "tagline": "Beyond darkness... beyond desolation... lies the greatest danger of all.",
  "id": 57158,
  "overview": "The Dwarves, Bilbo and Gandalf have successfully escaped the Misty Mountains, and Bilbo has gained the One Ring. They all continue their journey to get their gold back from the Dragon, Smaug.",
  "releaseDate": "2013-12-11",
  "runtime": 161,
  "companies": [
    "New Line Cinema",
    "Metro-Goldwyn-Mayer",
    "WingNut Films"
  ],
  "genres": [
    "Fantasy",
    "Adventure",
    "Action"
  ]
}