{
  "title": "The Usual Suspects",
  "tagline": "Five criminals. One line up. No coincidence.",
  "id": 629,
  "overview": "Held in an L.A. interrogation room, Verbal Kint attempts to convince the feds that a mythic crime lord, Keyser Soze, not only exists, but was also responsible for drawing him and his four partners into a multi-million dollar heist that ended with an explosion in San Pedro harbor – leaving few survivors. Verbal lures his interrogators with an incredible story of the crime lord's almost supernatural prowess.",
  "releaseDate": "1995-07-19",
  "runtime": 106,
  "companies": [
    "Bad Hat Harry Productions",
    "Blue Parrot Productions"
  ],
  "genres": [
    "Drama",
    "Crime",
    "Thriller"
  ]
}