{
  "title": "You've Got Mail",
  "tagline": "Someone you pass on the street may already be the love of your life.",
  "id": 9489,
  "overview": "Book superstore magnate Joe Fox and independent book shop owner Kathleen Kelly fall in love in the anonymity of the Internet—both blissfully unaware that he's trying to put her out of business.",
  "releaseDate": "1998-12-18",
  "runtime": 119,
  "companies": [
    "Warner Bros. Pictures",
    "The Donners' Company"
  ],
  "genres": [
    "Comedy",
    "Romance"
  ]
}