{
  "title": "RoboCop",
  "tagline": "Part man, part machine, all cop.",
  "id": 5548,
  "overview": "In a violent, near-apocalyptic Detroit, evil corporation Omni Consumer Products wins a contract from the city government to privatize the police force. To test their crime-eradicating cyborgs, the company leads street cop Alex Murphy into an armed confrontation with crime lord Boddicker so they can use his body to support their untested RoboCop prototype. But when RoboCop learns of the company's nefarious plans, he turns on his masters.",
  "releaseDate": "1987-07-17",
  "runtime": 102,
  "companies": [
    "Orion Pictures",
    "Jon Davison Productions"
  ],
  "genres": [
    "Action",
    "Thriller",
    "Science Fiction"
  ]
}